novikovtv_parser_fns/__init__.py
novikovtv_parser_fns/parser/__init__.py
novikovtv_parser_fns/parser/config.py
novikovtv_parser_fns/parser/constants.py
novikovtv_parser_fns/parser/exceptions.py
novikovtv_parser_fns/parser/nalog.py
novikovtv_parser_fns/parser/captcha/__init__.py
novikovtv_parser_fns/parser/captcha/ai.py
novikovtv_parser_fns/parser/captcha/helpers.py
novikovtv_parser_fns/parser/captcha/solver.py
novikovtv_parser_fns/parser/captcha/ml_models/68_percents.dat
novikovtv_parser_fns/parser/captcha/ml_models/68_percents.keras
novikovtv_parser_fns/parser/models/captcha.py
novikovtv_parser_fns/parser/models/search.py
novikovtv_parser_fns-1.0.7.dist-info/METADATA
novikovtv_parser_fns-1.0.7.dist-info/WHEEL
novikovtv_parser_fns-1.0.7.dist-info/licenses/LICENSE
novikovtv_parser_fns-1.0.7.dist-info/RECORD
